{
    "transcript_date": "December 21, 2016",
    "health_discussed": "Yes",
    "health_discussed_people_names": "Mwakirunge residents",
    "health_data_information_systems_discussed": "No",
    "health_data_information_systems_summary": "",
    "health_data_challenges": "Lack of access to healthcare, hazardous living conditions, discrimination, vulnerability to violence",
    "health_service_delivery_improvement_recommendations": "Equipped health centers near the dump site, Cost of treatment from dumpsite-related diseases to be scrapped off, Increase community health workers, Avail emergency and referral services for emergencies near the dumpsite, Avail rabies vaccine and specialized respiratory drugs, Regulate companies that dump at the site, Provide rescue and counseling services for girls raped at the dumpsite",
    "health_sector_decisions": "Formation of an Ad hoc committee to look into the challenges and recommendations facing the Mwakirunge community",
    "health_evidence_base": "Memorandum of challenges and recommendations from Mwakirunge residents",
    "health_evidence_requested": "Health services demands and recommendations"
}