{
    "health_sector_discussed": "No",
    "health_sector_discussed_people_names": "",
    "health_data_information_systems_discussed": "No",
    "health_data_information_systems_summary": "",
    "health_data_challenges": "Access to cheap fertilizer benefiting specific areas only, contract healthcare workers in need of permanent positions",
    "health_service_delivery_improvement_recommendations": "Consider permanent positions for contract healthcare workers, organize fertilizer distribution to benefit all farmers, support potato farmers facing challenges with middlemen",
    "health_sector_decisions": "No decisions.",
    "health_evidence_base": "Governor's speech and observations in the county",
    "health_evidence_requested": "No specific health sector information requested"
}